static_website/__init__.py
static_website/static_website.py
cdk_static_website-0.1.0.dist-info/METADATA
cdk_static_website-0.1.0.dist-info/WHEEL
cdk_static_website-0.1.0.dist-info/top_level.txt
cdk_static_website-0.1.0.dist-info/RECORD
